Metadata-Version: 2.1
Name: PythonRequire
Version: 0.0.0
Summary: A require() function in python.
Home-page: UNKNOWN
License: UNKNOWN
Platform: UNKNOWN
